<annotation>
	<folder>image</folder>
	<filename>1865.tif</filename>
	<path>D:\xianweijing\样本\image\1865.tif</path>
	<source>
		<database>Unknown</database>
	</source>
	<size>
		<width>2592</width>
		<height>1944</height>
		<depth>3</depth>
	</size>
	<segmented>0</segmented>
	<object>
		<name>Starch granules</name>
		<pose>Unspecified</pose>
		<truncated>0</truncated>
		<difficult>0</difficult>
		<bndbox>
			<xmin>1043</xmin>
			<ymin>736</ymin>
			<xmax>1608</xmax>
			<ymax>1405</ymax>
		</bndbox>
	</object>
</annotation>
