<annotation>
	<folder>image</folder>
	<filename>658.tif</filename>
	<path>D:\xianweijing\样本\image\658.tif</path>
	<source>
		<database>Unknown</database>
	</source>
	<size>
		<width>2592</width>
		<height>1944</height>
		<depth>3</depth>
	</size>
	<segmented>0</segmented>
	<object>
		<name>Cork cells</name>
		<pose>Unspecified</pose>
		<truncated>0</truncated>
		<difficult>0</difficult>
		<bndbox>
			<xmin>84</xmin>
			<ymin>468</ymin>
			<xmax>2466</xmax>
			<ymax>1900</ymax>
		</bndbox>
	</object>
</annotation>
